feature_flag/core/__init__.py
feature_flag/core/base_repository.py
feature_flag/core/cache.py
feature_flag/core/decorators.py
feature_flag/core/exceptions.py
feature_flag/models/__init__.py
feature_flag/models/feature_flag.py
feature_flag/notification/__init__.py
feature_flag/notification/change_status.py
feature_flag/notification/notifier.py
feature_flag/notification/slack_notifier.py
feature_flag/repositories/__init__.py
feature_flag/repositories/postgres_repository.py
feature_flag/services/__init__.py
feature_flag/services/feature_flag_service.py
spartan_module_feature_flag-0.4.1.dist-info/LICENSE
spartan_module_feature_flag-0.4.1.dist-info/METADATA
spartan_module_feature_flag-0.4.1.dist-info/WHEEL
spartan_module_feature_flag-0.4.1.dist-info/RECORD
